schellma/__init__.py
schellma/__main__.py
schellma/constants.py
schellma/converters.py
schellma/demo_features.py
schellma/exceptions.py
schellma/logger.py
schellma/py.typed
schellma/utils.py
schellma-0.3.0.dist-info/METADATA
schellma-0.3.0.dist-info/WHEEL
schellma-0.3.0.dist-info/licenses/LICENSE
schellma-0.3.0.dist-info/RECORD
