Metadata-Version: 2.4
Name: schellma
Version: 0.3.0
Summary: Clean, simplified schemas from Pydantic models for LLM prompts - less verbose than JSON Schema
Project-URL: Homepage, https://github.com/andrader/schellma
Project-URL: Documentation, https://andrader.github.io/schellma/
Project-URL: Repository, https://github.com/andrader/schellma.git
Project-URL: Issues, https://github.com/andrader/schellma/issues
Project-URL: Changelog, https://github.com/andrader/schellma/releases
Author-email: Rubens <38709237+andrader@users.noreply.github.com>
Maintainer-email: Rubens <38709237+andrader@users.noreply.github.com>
License: MIT
License-File: LICENSE
Keywords: ai,clean-schema,language-models,llm,prompts,pydantic,schema
Classifier: Development Status :: 4 - Beta
Classifier: Intended Audience :: Developers
Classifier: License :: OSI Approved :: MIT License
Classifier: Operating System :: OS Independent
Classifier: Programming Language :: Python :: 3
Classifier: Programming Language :: Python :: 3.11
Classifier: Programming Language :: Python :: 3.12
Classifier: Programming Language :: Python :: 3.13
Classifier: Topic :: Scientific/Engineering :: Artificial Intelligence
Classifier: Topic :: Software Development :: Code Generators
Classifier: Topic :: Software Development :: Libraries :: Python Modules
Classifier: Typing :: Typed
Requires-Python: >=3.11
Requires-Dist: pydantic>=2.0.0
